gpstime/__init__.py
gpstime/__main__.py
gpstime/__version__.py
gpstime/leaps.py
gpstime/test.py
gpstime-0.8.2.data/scripts/gpstime
gpstime-0.8.2.dist-info/COPYING
gpstime-0.8.2.dist-info/COPYING-GPL-3
gpstime-0.8.2.dist-info/METADATA
gpstime-0.8.2.dist-info/WHEEL
gpstime-0.8.2.dist-info/top_level.txt
gpstime-0.8.2.dist-info/RECORD
